{
  "categories": [
    "Electronics",
    "Sports and hobbies",
    "Goods for gamers",
    "Computer accessories",
    "Gaming chairs",
    "Cooking utensils",
    "Perfumery",
    "Kids toys",
    "Books"
  ],
  "addData": [
    35
  ],
  "products": [
    {
      "id": 1,
      "name": "Apple iPhone 14 Plus",
      "title": "Apple iPhone 14 Plus 512 GB eSim (Midnight)",
      "category": "Electronics",
      "slug": {
        "slug": "apple-iphone-14-plus",
        "category": "electronics"
      },
      "description": "Meet the new iPhone 14 Plus. Big and more. Incredible autonomy of work. A unique camera. All this in your new iPhone 14 Plus. The use of this phone is possible only with the presence of an eSim (electronic SIM card)",
      "price": 1139,
      "stars": 4.5,
      "images": [
        "https://www.istore.ua/upload/iblock/05e/1cgduywjdtn8u7oy1wionpqkhrr5lkn1/14_plus_spase_black_3_is.png",
        "https://www.istore.ua/upload/iblock/1a1/xbqdnppkshuterhj6dyihjz0soe83yas/14_plus_spase_black_2_is.png",
        "https://www.istore.ua/upload/iblock/356/ss92qfql8d5fan951w751vw2k7xrc2k7/14_plus_spase_black_1_is.png"
      ],
      "reviews": [
        {
          "id": "1689509801710",
          "user": {
            "image": "",
            "name": "kononucenkosasa4004@gmail.com"
          },
          "stars": 3.5,
          "message": "cool product"
        },
        {
          "id": "1689510028906",
          "user": {
            "image": "",
            "name": "kononucenkosasa4004@gmail.com"
          },
          "stars": 5,
          "message": "very nice"
        },
        {
          "id": "1690468543580",
          "user": {
            "image": "",
            "name": "kononucenkosasa4004@gmail.com"
          },
          "stars": 3,
          "message": "nice"
        }
      ]
    },
    {
      "id": 2,
      "name": "Apple iPad Pro",
      "title": "Apple iPad Pro 12.9 2022 Wi-Fi+Cellular 2 TB M2 Silver",
      "category": "Electronics",
      "slug": {
        "slug": "apple-ipad-pro",
        "category": "electronics"
      },
      "description": "Amazing performance. An incredibly advanced display. Ultra-fast wireless connection. New level of Apple Pencil capabilities. Powerful new features in iPadOS 16. The ultimate iPad experience.",
      "price": 1907,
      "stars": 3.8,
      "images": [
        "https://www.istore.ua/upload/iblock/829/tmnfw1wgamc0aoik9auyn1higp6syno3/MNY03_7_is.png",
        "https://www.istore.ua/upload/iblock/715/qn20at4242cf3divw62hlf09z98u9jgz/MNY03_6_is.png",
        "https://www.istore.ua/upload/iblock/43f/kq3m3ooe84x9r5wdfmnow398qs1kq5or/MNY03_5_is.png",
        "https://www.istore.ua/upload/iblock/f37/6ehktfkdouwudcg3zcompq17euzk6pfo/MNY03_4_is.png",
        "https://www.istore.ua/upload/iblock/3a6/l4gmwtplf61ogul0thf3u1uj1tfwzge4/MNY03_2_is.png"
      ],
      "reviews": [
        {
          "id": "1689527345254",
          "user": {
            "image": "",
            "name": "kononucenkosasa4004@gmail.com"
          },
          "stars": 3,
          "message": "cool product\n"
        }
      ]
    },
    {
      "id": 3,
      "name": "Apple MacBook Air 15",
      "title": "Apple MacBook Air 15 2023, 512 GB M2 Space Gray",
      "category": "Electronics",
      "slug": {
        "slug": "apple-macbook-air-15",
        "category": "electronics"
      },
      "description": "Impressively large. Incredibly thin. With the new 15-inch MacBook Air - more space for your favorite things thanks to the large Liquid Retina display Equipped with a productive M2 chip that increases battery life up to 18 hours, the New MacBook Air is lightning-fast performance in an ultraportable design.",
      "price": 1771,
      "stars": 4.2,
      "images": [
        "https://www.istore.ua/upload/iblock/257/c4t38nwwkyi7q801cdp0s6d354g1ptp2/MQKQ3_7_is.png",
        "https://www.istore.ua/upload/iblock/069/guv58epumpmze4997bo0l4prai69yokn/MQKQ3_1_is.png",
        "https://www.istore.ua/upload/iblock/8dd/oyi1ig2ukw4i8yvj35kmibfhm2e6df79/MQKQ3_6_is.png",
        "https://www.istore.ua/upload/iblock/24b/f5qcpccye7jem6bv57gjnldpu6tv80mn/MQKQ3_5_is.png",
        "https://www.istore.ua/upload/iblock/146/1eml4e61g6dd9a9lisf7f8qbt0afhpbn/MQKQ3_4_is.png",
        "https://www.istore.ua/upload/iblock/712/kabuboy8fjd6n9mnjdxzub1x6037k0u5/MQKQ3_2_is.png"
      ],
      "reviews": []
    },
    {
      "id": 4,
      "name": "Apple Watch SE",
      "title": "Apple Watch SE GPS 44mm Silver Aluminium Case with White Sport Band",
      "category": "Electronics",
      "slug": {
        "slug": "apple-watch-se",
        "category": "electronics"
      },
      "description": "Great Deal. Three stylish body colors. Powerful sensors for Innovative security features. Fast dual-core processor for extra performance. Apple Watch SE is now better than ever.",
      "price": 310,
      "stars": 4.9,
      "images": [
        "https://www.istore.ua/upload/resize_cache/iblock/a08/twxcgwrenhlz5e1a0nuaxfnm6zlf4fk3/920_600_1/Snimok-ekrana-2022_09_23-183748.png",
        "https://www.istore.ua/upload/resize_cache/iblock/abf/ozii2wu09qqc0x4a311wwlk4tdeabo3r/920_600_1/Snimok-ekrana-2022_09_23-183808.png",
        "https://www.istore.ua/upload/resize_cache/iblock/7aa/lkuhhn39n1a9wcrpqin3j7zgobszpkjg/920_600_1/Snimok-ekrana-2022_09_23-183821.png"
      ],
      "reviews": [
        {
          "id": "1690470437520",
          "user": {
            "image": "",
            "name": "sasha"
          },
          "stars": 4.5,
          "message": "nice clock!"
        }
      ]
    },
    {
      "id": 5,
      "name": "Belkin Lightning",
      "title": "Belkin USB Type-C to Lightning 2m",
      "category": "Electronics",
      "slug": {
        "slug": "belkin-lightning",
        "category": "electronics"
      },
      "description": "Enjoy fast charging and extra reliability with braided USB-C to Lightning cables.",
      "price": 27,
      "stars": 3.5,
      "images": [
        "https://www.istore.ua/upload/iblock/1a3/y3merq19my4dhsa89bdejxp6hy9sasjh/belkin_CAA004BT1MWH_4_is.jpg",
        "https://www.istore.ua/upload/iblock/4f5/bkrf317p64ftsp7b9onxz7z9qcfv2ll3/belkin_CAA004BT1MWH_3_is.jpg",
        "https://www.istore.ua/upload/iblock/9b8/fn2mu232tk1gqdfzgnb3u31rzvnyt45h/belkin_CAA004BT1MWH_2_is.jpg",
        "https://www.istore.ua/upload/iblock/62d/m7tzn49m88sgiadbaf9o2rfzipfwm8un/belkin_CAA004BT1MWH_1_is.jpg"
      ],
      "reviews": [
        {
          "id": "1689838321738",
          "user": {
            "image": "",
            "name": "kononucenkosasa4004@gmail.com"
          },
          "stars": 0,
          "message": "cool"
        }
      ]
    },
    {
      "id": 6,
      "name": "JBL Clip 4 Eco",
      "title": "JBL Clip 4 Eco Blue",
      "category": "Electronics",
      "slug": {
        "slug": "jbl-clip-4-eco",
        "category": "electronics"
      },
      "description": "JBL GO 3 is a new generation of ultra-portable speaker that combines the legendary JBL brand sound and bright modern design. It was created for those who do not want to part with their favorite music even for a second, and therefore has the most compact form factor, a waterproof case with protection against dust and moisture and a large battery. On a walk or during cycling, by the pool or on the beach - let your favorite music accompany you everywhere.",
      "price": 68,
      "stars": 4.1,
      "images": [
        "https://www.istore.ua/upload/iblock/b7c/cc88xdp8os3f3z3bywskliw9z5hwpkxr/JBLCLIP4ECOBLU_4_is.png",
        "https://www.istore.ua/upload/iblock/f29/ft4x39xh0z202rysm5wccn0dto1jlxnu/JBLCLIP4ECOBLU_3_is.png",
        "https://www.istore.ua/upload/iblock/abc/6oevhza3rl31p2rppo00em4b2fenreuh/JBLCLIP4ECOBLU_1_is.png",
        "https://www.istore.ua/upload/iblock/c8f/a7uadi47l05x79u9gdasdpp9ay4z4qn2/JBLCLIP4ECOBLU_2_is.png"
      ],
      "reviews": []
    },
    {
      "id": 7,
      "name": "Apple AirPods Pro 2",
      "title": "Apple AirPods Pro 2 Case",
      "category": "Electronics",
      "slug": {
        "slug": "apple-airpods-pro-2",
        "category": "electronics"
      },
      "description": "Apple provides an opportunity to restore lost components for less than half the cost of a new gadget. Few companies will provide you with such a service, because the loss of a gadget is not the reason for a bad gadget! And so you can restore your Apple AirPods, in this case the charging case.",
      "price": 87,
      "stars": 4.7,
      "images": [
        "https://www.istore.ua/upload/iblock/5ae/h3sjn69kkltztxjl4jy5uxgb951hz56t/MQD83_3_is.png",
        "https://www.istore.ua/upload/iblock/01c/w9paxyiuq1kl3mu5rrv14ksu5n136th3/MQD83_1_is.png",
        "https://www.istore.ua/upload/iblock/e51/zmykphs5a0y6dmyd9x1768fazerhojgz/MQD83_2_is.png",
        "https://www.istore.ua/upload/iblock/767/5xsoi814283r8szn22c9atfteyk0jwrl/MQD83_CASE_3_is.png"
      ],
      "reviews": []
    },
    {
      "id": 8,
      "name": "M1 Max Chip",
      "title": "M1 Max Chip with 10-Core CPU and 32-Core GPU, 32GB Memory, 2TB SSD",
      "category": "Electronics",
      "slug": {
        "slug": "m1-max-chip",
        "category": "electronics"
      },
      "description": "Mac Studio is a brand new productive Mac. In an extremely compact form, it combines incredible efficiency, a wealth of ports and unprecedented capabilities. Everything you need is at your fingertips. And any place can turn into your studio.",
      "price": 3243,
      "stars": 4,
      "images": [
        "https://www.istore.ua/upload/resize_cache/iblock/e51/dnmpvmeuyguexdmuvqvb38ud5yrlghtr/920_600_1/apple_mac_studio_m1_max_512gb_40091760047998.jpg",
        "https://www.istore.ua/upload/resize_cache/iblock/567/lzuzb5b2hqlljptok8wu1f4pfn39hv06/920_600_1/apple_mac_studio_m1_max_512gb_99033759990333.jpg",
        "https://www.istore.ua/upload/resize_cache/iblock/c0b/5wkwum53gv09ipfnbelp00hwn0hkxmfx/920_600_1/apple_mac_studio_m1_max_512gb_89585469762916.jpg",
        "https://www.istore.ua/upload/resize_cache/iblock/d07/q7y0pbur40j7fkxgjcikbab0ve7ck8ik/920_600_1/apple_mac_studio_m1_max_512gb_67718195837651.jpg"
      ],
      "reviews": []
    },
    {
      "id": 9,
      "name": "Apple MacBook Air 15",
      "title": "Apple MacBook Air 15 2023, 512 GB M2 Midnight",
      "category": "Electronics",
      "slug": {
        "slug": "apple-macbook-air-15",
        "category": "electronics"
      },
      "description": "Impressively large. Incredibly thin.With the new 15-inch MacBook Air - more space for your favorite things thanks to the large Liquid Retina display Equipped with a productive M2 chip that increases battery life up to 18 hours, the New MacBook Air offers lightning-fast performance in an ultraportable design.",
      "price": 1771,
      "stars": 4.9,
      "images": [
        "https://www.istore.ua/upload/iblock/df3/kdwq5xk306s1r6uo2hr13i4pf1slvon2/MQKX3_9_is.png",
        "https://www.istore.ua/upload/iblock/a36/2quv4io4xvfbkbgius17no99q33eqa92/MQKX3_3_is.png",
        "https://www.istore.ua/upload/iblock/0b9/b0yyjogm4fornxdkqloo9avzvadm5h3p/MQKX3_8_is.png",
        "https://www.istore.ua/upload/iblock/58b/bg6s4i3wnyi3j8szkk5l0lkmvn4qyhfk/MQKX3_7_is.png",
        "https://www.istore.ua/upload/iblock/5c8/jep7anulez2wknldw64lydcp10j4ut4k/MQKX3_6_is.png",
        "https://www.istore.ua/upload/iblock/284/4mu8fwywozerofl007diqsab1xpmejvu/MQKX3_5_is.png"
      ],
      "reviews": []
    },
    {
      "id": 10,
      "name": "Belkin Multiport Adapter",
      "title": "Belkin USB-C 7-in-1 Multiport Adapter",
      "category": "Electronics",
      "slug": {
        "slug": "belkin-multiport-adapter",
        "category": "electronics"
      },
      "description": "Create powerful work wherever you are with the USB-C 7-in-1 Multiport Adapter. Connect your MacBook, Chromebook or PC notebook to 4K video, PCs, peripherals, the Internet and more using the USB-C port.",
      "price": 114,
      "stars": 4.6,
      "images": [
        "https://www.istore.ua/upload/iblock/e1b/xifjoajdpdadcgo97m7rsya97ljyd4mi/INC009BTSGY_5_is.png",
        "https://www.istore.ua/upload/iblock/e49/xphgfgqz6ykhaucuuk5asqnm6rylasnm/INC009BTSGY_4_is.png",
        "https://www.istore.ua/upload/iblock/3e3/jfyh994utr65qlq94l39rscc8frz3m28/INC009BTSGY_3_is.png",
        "https://www.istore.ua/upload/iblock/271/ybwbe24i12ynl4lpowjrz64s3xr1pa11/INC009BTSGY_2_is.png",
        "https://www.istore.ua/upload/iblock/296/pse2a2gd0xswfxrskudt3bw8c7d8bmyi/INC009BTSGY_1_is.png"
      ],
      "reviews": []
    },
    {
      "id": 11,
      "name": "Gray's Bicycle Helmet",
      "title": "Gray's Bicycle Helmet Size L Matte Black-Red",
      "category": "Sports and hobbies",
      "slug": {
        "slug": "gray's-bicycle-helmet",
        "category": "sports-and-hobbies"
      },
      "description": "The Grey's Bicycle Helmet is a must-have accessory for cycling. Will soften and take the hit during the fall.",
      "price": 30,
      "stars": 3.2,
      "images": [
        "https://content1.rozetka.com.ua/goods/images/big/316111314.jpg",
        "https://content2.rozetka.com.ua/goods/images/big/316111313.jpg"
      ],
      "reviews": []
    },
    {
      "id": 12,
      "name": "Bicycle Discovery RIDER",
      "title": "Bicycle Discovery RIDER AM DD 26\" 13\" 2022 Graphite (m)",
      "category": "Sports and hobbies",
      "slug": {
        "slug": "bicycle-discovery-rider",
        "category": "sports-and-hobbies"
      },
      "description": "Our bikes will give you exactly what you expect from a good, quality, well-made product. Created by lovers of a healthy and active lifestyle, the bikes of our Ukrainian brand will give you a whole sea of ​​positive emotions. They can handle any task, because they were created by cyclists for the same cyclists. A daily bike ride through the forest or a fishing trip, your child's first bike steps or city riding - all this is the element of our bikes!",
      "price": 190,
      "stars": 3.5,
      "images": [
        "https://content.rozetka.com.ua/goods/images/big/315835894.jpg"
      ],
      "reviews": [
        {
          "id": "1690472204269",
          "user": {
            "image": "https://lh3.googleusercontent.com/a/AAcHTtcN3417hGBr6UOAgUOpFjoazdpgb2cWWKu2D5INLciqGg=s96-c",
            "name": "Олександр Кононученко"
          },
          "stars": 3,
          "message": "nice bike"
        }
      ]
    },
    {
      "id": 13,
      "name": "Handlebar grips",
      "title": "Grey's silicone handlebar grips 2 pcs 165 mm Red",
      "category": "Sports and hobbies",
      "slug": {
        "slug": "handlebar-grips",
        "category": "sports-and-hobbies"
      },
      "price": 4,
      "stars": 3.5,
      "images": [
        "https://content2.rozetka.com.ua/goods/images/big/172222095.jpg",
        "https://content2.rozetka.com.ua/goods/images/big/172222098.jpg",
        "https://content.rozetka.com.ua/goods/images/big/172222100.jpg"
      ],
      "reviews": []
    },
    {
      "id": 14,
      "name": "TOORX Indoor Cycle",
      "title": "TOORX Indoor Cycle SRX 80 EVO",
      "category": "Sports and hobbies",
      "slug": {
        "slug": "toorx-indoor-cycle",
        "category": "sports-and-hobbies"
      },
      "description": "Cycle simulator TOORX Indoor Cycle SRX 80EVO from the Italian manufacturer Garlando S.p.A. designed for intensive cardio training at home. The simulator has a shoe brake system with manual stepless load adjustment, as well as a modern computer with the necessary set of functions. A heavy 24 kg flywheel together with a belt drive ensure quiet operation of the simulator and sufficient load even for trained athletes. The spin bike is designed for weights up to 140 kg and is suitable for users up to 2 m tall. A chest strap for wireless heart rate measurement will be appropriate during training to monitor heart rate.",
      "price": 829,
      "stars": 0,
      "images": [
        "https://content1.rozetka.com.ua/goods/images/big/315057447.jpg",
        "https://content2.rozetka.com.ua/goods/images/big/315057459.jpg",
        "https://content2.rozetka.com.ua/goods/images/big/315057458.jpg",
        "https://content.rozetka.com.ua/goods/images/big/315057448.jpg",
        "https://content.rozetka.com.ua/goods/images/big/315057449.jpg",
        "https://content.rozetka.com.ua/goods/images/big/315057450.jpg",
        "https://content2.rozetka.com.ua/goods/images/big/315057451.jpg",
        "https://content2.rozetka.com.ua/goods/images/big/315057453.jpg",
        "https://content2.rozetka.com.ua/goods/images/big/315057456.jpg"
      ],
      "reviews": []
    },
    {
      "id": 15,
      "name": "PlayStation 5",
      "title": "PS5 PlayStation 5",
      "category": "Goods for gamers",
      "slug": {
        "slug": "playstation-5",
        "category": "goods-for-gamers"
      },
      "description": "Lightning-fast loading times with ultra-fast SSD storage, incredible immersion with tactile feedback, adaptive shutter releases and 3D audio, and amazing next-gen PlayStation® games. Incredibly powerful CPUs, GPUs, and an SSD with integrated I/O will redefine your PlayStation console experience. Connect your PlayStation VR to your PS5 console and play supported PS VR games. To set up your PS VR to work with your PS5 console, you'll need a PlayStation Camera4 for PS4 and a PlayStation Camera Adapter (not required). More information on how to get the adapter will be posted on PlayStation.com when the adapter becomes available.",
      "price": 613,
      "images": [
        "https://content1.rozetka.com.ua/goods/images/big/134042269.jpg",
        "https://content.rozetka.com.ua/goods/images/big/134042296.jpg",
        "https://content1.rozetka.com.ua/goods/images/big/219494175.jpg",
        "https://content2.rozetka.com.ua/goods/images/big/219494186.jpg",
        "https://content1.rozetka.com.ua/goods/images/big/219494958.jpg"
      ],
      "reviews": []
    },
    {
      "id": 16,
      "name": "Microsoft Xbox Series X",
      "title": "Microsoft Xbox Series X Game Console (RRT-00010)",
      "category": "Goods for gamers",
      "slug": {
        "slug": "microsoft-xbox-series-x",
        "category": "goods-for-gamers"
      },
      "description": "Microsoft Xbox Series X is a huge leap forward! The fastest and most powerful Xbox ever. Optimized for Series X|S Games built with the Xbox Series X|S Development Kit experience significant reductions in load times and stunning visuals at up to 120fps. Forward! From future adventures to current hobbies to classic games, the Xbox Series X is the best console to enjoy thousands of your favorite games across four generations of Xbox.",
      "price": 756,
      "images": [
        "https://content.rozetka.com.ua/goods/images/big/276682665.jpg",
        "https://content1.rozetka.com.ua/goods/images/big/276682666.jpg",
        "https://content1.rozetka.com.ua/goods/images/big/276682667.jpg",
        "https://content.rozetka.com.ua/goods/images/big/276682668.jpg"
      ],
      "reviews": []
    },
    {
      "id": 17,
      "name": "MSI GeForce RTX 3060 Gaming X",
      "title": "Video card MSI PCI-Ex GeForce RTX 3060 Gaming X 12G 12GB GDDR6 (192bit) (1837/15000) (HDMI, 3 x DisplayPort) (RTX 3060 GAMING X 12G)",
      "category": "Computer accessories",
      "slug": {
        "slug": "msi-geforce-rtx-3060-gaming-x",
        "category": "computer-accessories"
      },
      "description": "The latest incarnation of MSI's iconic Gaming Series is the same combination of high speed, efficient cooling and impeccable aesthetics that hardcore gamers have long loved. This graphics card will let you run the latest games while staying cool and quiet, just the way you want it. It's time to show yourself in the best light! Synchronize your graphics card lighting with the rest of your computer system for an authentic gaming experience. Turning it off is as easy as turning off the lights in the room.",
      "price": 446,
      "salePrice": 430,
      "images": [
        "https://content.rozetka.com.ua/goods/images/big/74284841.jpg",
        "https://content1.rozetka.com.ua/goods/images/big/74284842.jpg",
        "https://content.rozetka.com.ua/goods/images/big/74284843.jpg",
        "https://content2.rozetka.com.ua/goods/images/big/74284844.jpg",
        "https://content2.rozetka.com.ua/goods/images/big/74284845.jpg"
      ],
      "reviews": []
    },
    {
      "id": 18,
      "name": "MSI GeForce RTX 4080 Suprim",
      "title": "Video card MSI PCI-Ex GeForce RTX 4080 Suprim X 16GB GDDR6X (256bit) (22400) (HDMI, 3 x DisplayPort) (GeForce RTX 4080 16GB SUPRIM X)",
      "category": "Computer accessories",
      "slug": {
        "slug": "msi-geforce-rtx-4080-suprim",
        "category": "computer-accessories"
      },
      "description": "Change the game! The SUPRIM series of video cards is a new level. Their highest class is manifested in the use of selected materials and advanced engineering solutions. TRI-FROZR 3S. Cooling system. Updated fans, airflow management system and many other innovations make TRI-FROZR 3S the best MSI air cooler at the moment. Fans TORX 5.0 Design improvements implemented in TORX 5.0 fans increase airflow - it is +23% more powerful than axial fans. Metal reinforcement plate A strong metal plate on the back of the video card serves as part of the cooling system. Thanks to thermal pads, it acts as a radiator, and the ventilation holes made in it allow hot air to escape.",
      "price": 1590,
      "salePrice": 1474,
      "images": [
        "https://content2.rozetka.com.ua/goods/images/big/327548674.png",
        "https://content.rozetka.com.ua/goods/images/big/327548676.png",
        "https://content1.rozetka.com.ua/goods/images/big/327548677.png",
        "https://content1.rozetka.com.ua/goods/images/big/327548678.png",
        "https://content1.rozetka.com.ua/goods/images/big/327548679.png",
        "https://content1.rozetka.com.ua/goods/images/big/327548680.png",
        "https://content2.rozetka.com.ua/goods/images/big/327548681.png",
        "https://content1.rozetka.com.ua/goods/images/big/327548682.png"
      ],
      "reviews": []
    },
    {
      "id": 19,
      "name": "BenQ Zowie XL2540K Dark Grey",
      "title": "Monitor 24.5 BenQ Zowie XL2540K Dark Grey",
      "category": "computer-accessories",
      "slug": {
        "slug": "benq-zowie-xl2540k-dark-grey",
        "category": "Computer accessories"
      },
      "description": "The new generation of the iconic XL Series esports monitors will make gaming even more comfortable and allow gamers to focus more on the game. 240Hz high refresh rate for maximum fluidity The ZOWIE XL2540K eSports Monitor features the highest refresh rate of 240Hz to ensure you experience minimal latency. Notice every detail and enjoy smooth gameplay, even in fast-paced scenes. The smoothest possible display of fast-moving objects, instant reaction to the player's actions, accurate tracking of the cursor movement will make your victory inevitable!",
      "price": 413,
      "images": [
        "https://content2.rozetka.com.ua/goods/images/big/160902004.jpg",
        "https://content1.rozetka.com.ua/goods/images/big/160902006.jpg",
        "https://content2.rozetka.com.ua/goods/images/big/160902007.jpg",
        "https://content1.rozetka.com.ua/goods/images/big/160902008.jpg",
        "https://content.rozetka.com.ua/goods/images/big/160902009.jpg",
        "https://content2.rozetka.com.ua/goods/images/big/160902010.jpg"
      ],
      "reviews": []
    },
    {
      "id": 20,
      "name": "DXRacer Air PRO",
      "title": "Chair DXRacer Air PRO mesh, aluminum base White-red",
      "category": "Gaming chairs",
      "slug": {
        "slug": "dxracer-air-pro",
        "category": "gaming-chairs"
      },
      "description": "Memory foam headrest Made from highly resilient memory foam, the headrest conforms to the shape of your neck and adapts to your every movement for perfect neck support and comfort. New premium quality mesh The ultra-breathable mesh allows for good airflow and reduces heat and moisture build-up, keeping gamers fresh during long, intense gaming sessions. Exclusive strength Eco-friendly, durable mesh is combined with exclusive racecar-specific springs to create lightweight, responsive cushioning and extended seat life.",
      "price": 486,
      "salePrice": 432,
      "images": [
        "https://content.rozetka.com.ua/goods/images/big/278835979.jpg",
        "https://content2.rozetka.com.ua/goods/images/big/278835980.jpg",
        "https://content2.rozetka.com.ua/goods/images/big/278835981.jpg",
        "https://content.rozetka.com.ua/goods/images/big/278835982.jpg",
        "https://content2.rozetka.com.ua/goods/images/big/278835983.jpg",
        "https://content2.rozetka.com.ua/goods/images/big/278835984.jpg",
        "https://content2.rozetka.com.ua/goods/images/big/278835985.jpg",
        "https://content.rozetka.com.ua/goods/images/big/278835986.jpg"
      ],
      "reviews": []
    },
    {
      "id": 21,
      "name": "DXRacer G Series D8100 Black-Red",
      "title": "DXRacer G Series D8100 Gamer Chair Black-Red",
      "category": "Gaming chairs",
      "slug": {
        "slug": "dxracer-g-series-d8100-black-red",
        "category": "gaming-chairs"
      },
      "description": "Each DXRacer G Series chair is designed and handcrafted with thoughtful details and high quality materials. The premium PU leather of this chair not only helps to create the support you need for your back while maintaining softness, but also promotes ventilation. Эргономичные регулируемые подлокотники 4D перемещаются вверх/вниз, влево/вправо, вперед/назад, а также могут поворачиваться вокруг своей оси, чтобы вы смогли выбрать их идеальное положение для себя, обеспечивая надлежащую амортизацию между рукой и локтем.",
      "price": 312,
      "salePrice": 258,
      "images": [
        "https://content1.rozetka.com.ua/goods/images/big/213131301.jpg",
        "https://content.rozetka.com.ua/goods/images/big/213131302.jpg",
        "https://content2.rozetka.com.ua/goods/images/big/213131303.jpg",
        "https://content.rozetka.com.ua/goods/images/big/213131304.jpg",
        "https://content1.rozetka.com.ua/goods/images/big/213131305.jpg",
        "https://content1.rozetka.com.ua/goods/images/big/213131306.jpg",
        "https://content.rozetka.com.ua/goods/images/big/213131307.jpg",
        "https://content1.rozetka.com.ua/goods/images/big/213131308.jpg",
        "https://content.rozetka.com.ua/goods/images/big/213131309.jpg"
      ],
      "reviews": []
    },
    {
      "id": 22,
      "name": "Anda Seat T-Pro 2 Size XL Linen Fabric",
      "title": "Gaming chair Anda Seat T-Pro 2 Size XL Linen Fabric Grey/Black",
      "category": "Gaming chairs",
      "slug": {
        "slug": "anda-seat-t-pro-2-size-xl-linen-fabric",
        "category": "gaming-chairs"
      },
      "description": "An armchair whose design captures, taking the game to a new level. Improves posture, relieves stress from the back. Facilitates long and heavy gaming sessions. AD Alpha linen fabric. Stain resistant, easy to clean. Retains shape. Environmentally friendly, does not contain harmful elements. Backrest tilt adjustable 90 ~ 160 degrees with corner lock in any position. AD+Recline supports multifunction tilt.",
      "price": 462,
      "salePrice": 421,
      "images": [
        "https://content.rozetka.com.ua/goods/images/big/334500296.jpg",
        "https://content1.rozetka.com.ua/goods/images/big/334500299.jpg",
        "https://content1.rozetka.com.ua/goods/images/big/334500302.jpg",
        "https://content.rozetka.com.ua/goods/images/big/334500304.jpg",
        "https://content.rozetka.com.ua/goods/images/big/334500306.jpg",
        "https://content1.rozetka.com.ua/goods/images/big/334500309.jpg",
        "https://content2.rozetka.com.ua/goods/images/big/334500311.jpg",
        "https://content1.rozetka.com.ua/goods/images/big/334500314.jpg",
        "https://content1.rozetka.com.ua/goods/images/big/334500316.jpg",
        "https://content1.rozetka.com.ua/goods/images/big/334500318.jpg"
      ],
      "reviews": []
    },
    {
      "id": 23,
      "name": "Anda Seat Phantom 3 Size L Black",
      "title": "Gaming chair Anda Seat Phantom 3 Size L Black",
      "category": "Gaming chairs",
      "slug": {
        "slug": "anda-seat-phantom-3-size-l-black",
        "category": "gaming-chairs"
      },
      "description": "An armchair whose design captures, taking the game to a new level. Improves posture, relieves stress from the back. Facilitates long and heavy gaming sessions. AD Alpha linen fabric. Stain resistant, easy to clean. Retains shape. Environmentally friendly, does not contain harmful elements. Backrest tilt adjustable 90 ~ 160 degrees with corner lock in any position. AD+Recline supports multifunction tilt.",
      "price": 326,
      "salePrice": 299,
      "images": [
        "https://content2.rozetka.com.ua/goods/images/big/334500753.jpg",
        "https://content2.rozetka.com.ua/goods/images/big/334500755.jpg",
        "https://content2.rozetka.com.ua/goods/images/big/334500756.jpg",
        "https://content2.rozetka.com.ua/goods/images/big/334500757.jpg",
        "https://content2.rozetka.com.ua/goods/images/big/334500758.jpg",
        "https://content1.rozetka.com.ua/goods/images/big/334500759.jpg",
        "https://content2.rozetka.com.ua/goods/images/big/334500760.jpg",
        "https://content.rozetka.com.ua/goods/images/big/334500761.jpg",
        "https://content1.rozetka.com.ua/goods/images/big/334500762.jpg",
        "https://content1.rozetka.com.ua/goods/images/big/334500763.jpg",
        "https://content2.rozetka.com.ua/goods/images/big/334500764.jpg"
      ],
      "reviews": []
    },
    {
      "id": 24,
      "name": "Barsky Game Mesh Gray",
      "title": "Gaming chair Barsky Game Mesh Gray",
      "category": "Gaming chairs",
      "slug": {
        "slug": "barsky-game-mesh-gray",
        "category": "gaming-chairs"
      },
      "description": "Seat dimensions 52 - 49 cm",
      "price": 812,
      "images": [
        "https://content1.rozetka.com.ua/goods/images/big/339929400.jpg",
        "https://content2.rozetka.com.ua/goods/images/big/335332111.jpg",
        "https://content.rozetka.com.ua/goods/images/big/335332112.jpg",
        "https://content2.rozetka.com.ua/goods/images/big/335332113.jpg",
        "https://content1.rozetka.com.ua/goods/images/big/335332114.jpg",
        "https://content2.rozetka.com.ua/goods/images/big/335332116.jpg",
        "https://content.rozetka.com.ua/goods/images/big/335332118.jpg",
        "https://content1.rozetka.com.ua/goods/images/big/335332121.jpg",
        "https://content2.rozetka.com.ua/goods/images/big/335332123.jpg",
        "https://content.rozetka.com.ua/goods/images/big/335332125.jpg",
        "https://content.rozetka.com.ua/goods/images/big/335332127.jpg"
      ],
      "reviews": []
    },
    {
      "id": 25,
      "name": "Processor Intel Core i7-13700KF",
      "title": "Processor Intel Core i7-13700KF 3.4GHz/30MB s1700 BOX",
      "category": "Computer accessories",
      "slug": {
        "slug": "processor-intel-core-i7-13700kf",
        "category": "computer-accessories"
      },
      "description": "Unlocked 13th Gen Intel Core desktop processor optimized for enthusiast gamers and serious creators. Compatible with motherboards based on 700/600 series chipsets.",
      "price": 469,
      "images": [
        "https://content1.rozetka.com.ua/goods/images/big/291333489.jpg",
        "https://content.rozetka.com.ua/goods/images/big/291333493.jpg"
      ],
      "reviews": []
    },
    {
      "id": 26,
      "name": "Processor AMD Ryzen 5 5600",
      "title": "Processor AMD Ryzen 5 5600 3.5GHz/32MB sAM4 BOX",
      "category": "Computer accessories",
      "slug": {
        "slug": "processor-amd-ryzen-5-5600",
        "category": "computer-accessories"
      },
      "description": "The world's best desktop processor delivers superior gaming performance. An easy and fast way to expand your AMD Ryzen desktop storage and speed it up. A simple and powerful program for overclocking AMD Ryzen processors. For users who want to get the most out of their virtual reality experience, AMD offers high-performance Ryzen VR-Ready Premium processors.",
      "price": 157,
      "salePrice": 155,
      "images": [
        "https://content1.rozetka.com.ua/goods/images/big/267296945.jpg"
      ],
      "reviews": []
    },
    {
      "id": 27,
      "name": "Processor Intel Core i3-10105F",
      "title": "Processor Intel Core i3-10105F 3.7GHz/6MB s1200 BOX",
      "category": "Computer accessories",
      "slug": {
        "slug": "processor-intel-core-i3-10105f",
        "category": "computer-accessories"
      },
      "description": "New 10th Gen Intel Core i3-10105F processor codenamed Comet Lake microarchitecture. Designed for the Intel LGA 1200 desktop platform. Belongs to the Core i3 family of high-performance processors. The Intel Core i3-10105F is manufactured according to the 14nm process technology standard, has 4 cores that work in 8 threads with a nominal clock frequency of 3.7 GHz, 4.4 GHz in Turbo Boost mode. The level 3 cache is 6 MB. It has a 2-channel DDR4 memory controller.",
      "price": 91,
      "salePrice": 75,
      "images": [
        "https://content.rozetka.com.ua/goods/images/big/164924199.jpg",
        "https://content1.rozetka.com.ua/goods/images/big/164924200.jpg",
        "https://content1.rozetka.com.ua/goods/images/big/164924201.jpg"
      ],
      "reviews": []
    },
    {
      "id": 28,
      "name": "Processor Intel Core i5-13600K",
      "title": "Processor Intel Core i5-13600K 3.5GHz/24MB s1700 BOX",
      "category": "Computer accessories",
      "slug": {
        "slug": "processor-intel-core-i5-13600k",
        "category": "computer-accessories"
      },
      "description": "Unlocked 13th Gen Intel Core desktop processor optimized for enthusiast gamers and serious creators. Compatible with motherboards based on 700/600 series chipsets.",
      "price": 418,
      "salePrice": 379,
      "images": [
        "https://content.rozetka.com.ua/goods/images/big/291317668.jpg",
        "https://content2.rozetka.com.ua/goods/images/big/291317669.jpg"
      ],
      "reviews": []
    },
    {
      "id": 29,
      "name": "Processor Intel Core i9-13900KF",
      "title": "Processor Intel Core i9-13900KF 3.0GHz/36MB s1700 BOX",
      "category": "Computer accessories",
      "slug": {
        "slug": "processor-intel-core-i9-13900kf",
        "category": "computer-accessories"
      },
      "description": "Unlocked 13th Gen Intel Core desktop processor optimized for enthusiast gamers and serious creators. Compatible with motherboards based on 700/600 series chipsets.",
      "price": 898,
      "salePrice": 673,
      "images": [
        "https://content.rozetka.com.ua/goods/images/big/291345595.jpg",
        "https://content.rozetka.com.ua/goods/images/big/291345602.jpg"
      ],
      "reviews": []
    },
    {
      "id": 30,
      "name": "Processor AMD Ryzen 3 4100",
      "title": "Processor AMD Ryzen 3 4100 3.8GHz/4MB sAM4 BOX",
      "category": "Computer accessories",
      "slug": {
        "slug": "processor-amd-ryzen-3-4100",
        "category": "computer-accessories"
      },
      "description": "The new AMD Zen architecture uses a powerful execution engine and supports simultaneous multi-threading (SMT). Zen cores are designed to make efficient use of available microarchitecture resources for maximum computing performance. The new low-latency 3-level cache and new prefetching algorithms significantly reduce cache misses and increase throughput compared to the previous microarchitecture.",
      "price": 81,
      "salePrice": 68,
      "images": [
        "https://content1.rozetka.com.ua/goods/images/big/267293025.jpg",
        "https://content1.rozetka.com.ua/goods/images/big/267293026.jpg"
      ],
      "reviews": []
    },
    {
      "id": 31,
      "name": "Processor AMD Ryzen 9 7900",
      "title": "Processor AMD Ryzen 9 7900 3.7GHz/64MB sAM5 BOX",
      "category": "Computer accessories",
      "slug": {
        "slug": "processor-amd-ryzen-9-7900",
        "category": "computer-accessories"
      },
      "description": "The world's best desktop processor delivers superior gaming performance. An easy and fast way to expand your AMD Ryzen desktop storage and speed it up. A simple and powerful program for overclocking AMD Ryzen processors. For users who want to get the most out of their virtual reality experience, AMD offers high-performance Ryzen VR-Ready Premium processors.",
      "price": 569,
      "images": [
        "https://content2.rozetka.com.ua/goods/images/big/308584721.jpg"
      ],
      "reviews": []
    },
    {
      "id": 32,
      "name": "Processor AMD Ryzen 7 5800X",
      "title": "Processor AMD Ryzen 7 5800X 3.8GHz/32MB sAM4 BOX",
      "category": "Computer accessories",
      "slug": {
        "slug": "processor-amd-ryzen-7-5800x",
        "category": "computer-accessories"
      },
      "description": "The world's best desktop processor delivers superior gaming performance. An easy and fast way to expand your AMD Ryzen desktop storage and speed it up. A simple and powerful program for overclocking AMD Ryzen processors. For users who want to get the most out of their virtual reality experience, AMD offers high-performance Ryzen VR-Ready Premium processors.",
      "price": 341,
      "salePrice": 258,
      "images": [
        "https://content1.rozetka.com.ua/goods/images/big/35685183.jpg"
      ],
      "reviews": []
    },
    {
      "id": 33,
      "name": "WOK Tefal XL Intense",
      "title": "Frying pan WOK Tefal XL Intense 28 cm",
      "category": "Cooking utensils",
      "slug": {
        "slug": "wok-tefal-xl-intense",
        "category": "cooking-utensils"
      },
      "description": "Discover the perfect wok pan: the Tefal XL Intense cookware collection is designed to meet all your daily cooking needs, combining durable performance and large size for hearty daily meals. Everything you need for tasty and healthy food is within reach: a highly durable non-stick coating - very durable, environmentally friendly, helps save energy and water consumption when washing - advanced Thermo-signal technology for flawless results that do not require guesswork to start cooking, and Diffusion + base for perfectly homogeneous dishes.",
      "price": 39,
      "salePrice": 31,
      "images": [
        "https://content2.rozetka.com.ua/goods/images/big/63604575.jpg",
        "https://content2.rozetka.com.ua/goods/images/big/63604586.jpg",
        "https://content.rozetka.com.ua/goods/images/big/63604595.jpg",
        "https://content.rozetka.com.ua/goods/images/big/63604609.jpg"
      ],
      "reviews": []
    },
    {
      "id": 34,
      "name": "Krauff pot",
      "title": "Krauff pot set 6 items",
      "category": "Cooking utensils",
      "slug": {
        "slug": "krauff-pot",
        "category": "cooking-utensils"
      },
      "description": "The history of the Krauff cookware brand began over a hundred years ago in the city of Pforzheim, near Stuttgart, Germany. Craftsman Jorgen Krauff lived, worked and created his masterpieces in a small workshop. Jorgen always remembered his death and how she fried pork and dumplings, which he loved so much as a child. He always wants to help his mother, so the first frying pan is made with love and incredible meticulousness to the smallest detail, Jorgen, of course, made it especially for his mother.",
      "price": 101,
      "salePrice": 76,
      "images": [
        "https://content.rozetka.com.ua/goods/images/big/317952333.jpg",
        "https://content2.rozetka.com.ua/goods/images/big/317952334.jpg",
        "https://content1.rozetka.com.ua/goods/images/big/317952335.jpg",
        "https://content2.rozetka.com.ua/goods/images/big/317952336.jpg",
        "https://content1.rozetka.com.ua/goods/images/big/317952337.jpg",
        "https://content.rozetka.com.ua/goods/images/big/317952338.jpg",
        "https://content.rozetka.com.ua/goods/images/big/317952339.jpg",
        "https://content.rozetka.com.ua/goods/images/big/317952342.jpg",
        "https://content.rozetka.com.ua/goods/images/big/317952343.jpg"
      ],
      "reviews": []
    },
    {
      "id": 35,
      "name": "Fondue set Ardesto",
      "title": "Fondue set Ardesto 10 items",
      "category": "Cooking utensils",
      "slug": {
        "slug": "fondue-set-ardesto",
        "category": "cooking-utensils"
      },
      "description": "Ardesto is a brand of high-quality and reliable household appliances, climate control equipment, dishes and home accessories. Collaboration with leading development centers has made it possible to implement the most innovative and bold trends in the world of industrial and domestic design. Ardesto products will complement and harmoniously fit into any interior. Production facilities are located in Europe, Turkey and China. The equipment of the plants meets international standards, and all Ardesto products undergo strict quality control and are certified according to European and Ukrainian standards.",
      "price": 39,
      "salePrice": 21,
      "images": [
        "https://content1.rozetka.com.ua/goods/images/big/36297557.jpg",
        "https://content1.rozetka.com.ua/goods/images/big/36297527.jpg",
        "https://content.rozetka.com.ua/goods/images/big/36297544.jpg",
        "https://content.rozetka.com.ua/goods/images/big/36297549.jpg"
      ],
      "reviews": []
    },
    {
      "id": 36,
      "name": "Chanel Chance Eau Tendre",
      "title": "Chanel Chance Eau Tendre Eau de Parfum for Women 50 ml",
      "category": "Perfumery",
      "slug": {
        "slug": "chanel-chance-eau-tendre",
        "category": "perfumery"
      },
      "description": "Since Chanel Chance Eau Tendre is very touching and almost weightless, it will not prevail over the woman who has chosen it, but will only very delicately and gently help to complement her image. At the same time, he may not be obvious to his mistress, but those who will be nearby will definitely notice him. Weakness and femininity, which are the main weapons of every woman in the struggle for the heart of her beloved man - these are the qualities that, in addition to this fragrance, will most noticeably stand out in a woman and become more obvious to others.",
      "price": 198,
      "salePrice": 158,
      "images": [
        "https://content1.rozetka.com.ua/goods/images/big/18027487.jpg",
        "https://content2.rozetka.com.ua/goods/images/big/18027511.jpg"
      ],
      "reviews": []
    },
    {
      "id": 37,
      "name": "Lacoste Pour Homme",
      "title": "Tester Eau de toilette for men Lacoste Pour Homme 100 ml",
      "category": "Perfumery",
      "slug": {
        "slug": "lacoste-pour-homme",
        "category": "perfumery"
      },
      "description": "Eau de toilette Lacoste Pour Homme has long been a \"must have\" in the collections of many respectable men. Bearing such a simple name, this perfume creation has already managed to conquer the world. A simple glass bottle is decorated with the image of a crocodile - the signature emblem of the house of Lacoste. There is nothing superfluous and overly pretentious in the external design, but inside there is a unique aroma that can inspire and inspire.",
      "price": 51,
      "images": [
        "https://content.rozetka.com.ua/goods/images/big/13556134.jpg"
      ],
      "reviews": []
    },
    {
      "id": 38,
      "name": "Antonio Banderas Blue Seduction",
      "title": "Eau de toilette for women Antonio Banderas Blue Seduction for Women 200 ml",
      "category": "Perfumery",
      "slug": {
        "slug": "antonio-banderas-blue-seduction",
        "category": "perfumery"
      },
      "description": "Blue Seduction for Women expresses the Latin American light, exciting attitude to what is happening, the ability and desire to enjoy every day. The Blue Sedation woman is glamorous and simple at the same time, she is spontaneous and unpredictable, she enjoys every moment. She boldly uses her sexuality and sensuality, she, like in chess, starts and wins, while she is always sincere.",
      "price": 34,
      "salePrice": 24,
      "images": [
        "https://content1.rozetka.com.ua/goods/images/big/50142872.jpg",
        "https://content2.rozetka.com.ua/goods/images/big/50142876.jpg"
      ],
      "reviews": []
    },
    {
      "id": 39,
      "name": "Car ZIPP Toys CAM",
      "title": "Car ZIPP Toys CAM buggy with camera Black",
      "category": "Kids toys",
      "slug": {
        "slug": "car-zipp-toys-cam",
        "category": "kids-toys"
      },
      "description": "Despite its small dimensions, the model is equipped with a high suspension and soft shock absorbers, for the ability to easily overcome absolutely any obstacles and bumps. Hollow rubber wheels provide better grip and stability while riding. Buggy can reach speeds up to 6 km / h.",
      "price": 46,
      "images": [
        "https://content2.rozetka.com.ua/goods/images/big/219683413.jpg",
        "https://content2.rozetka.com.ua/goods/images/big/219683412.jpg",
        "https://content2.rozetka.com.ua/goods/images/big/219683411.jpg",
        "https://content1.rozetka.com.ua/goods/images/big/219683410.jpg",
        "https://content1.rozetka.com.ua/goods/images/big/219683409.jpg",
        "https://content1.rozetka.com.ua/goods/images/big/219683407.jpg",
        "https://content2.rozetka.com.ua/goods/images/big/219683406.jpg"
      ],
      "reviews": []
    },
    {
      "id": 40,
      "name": "Soft toy Tigres Bunny Star",
      "title": "Soft toy Tigres Bunny Star 29 cm",
      "category": "Kids toys",
      "slug": {
        "slug": "soft-toy-tigres-bunny-star",
        "category": "kids-toys"
      },
      "description": "Toy Bunny \"Star\" is soft and tender, ideal for babies from birth. The balling tummy will attract the attention of the baby and will develop tactile sensations, and the special granules used when filling the toy will develop fine motor skills of the hands, which is responsible for the child's speech. Safe materials, high-quality embroidery, bright colors and original design - the \"Star\" bunny will appeal to everyone.",
      "price": 15,
      "images": [
        "https://content2.rozetka.com.ua/goods/images/big/148931556.jpg",
        "https://content.rozetka.com.ua/goods/images/big/148931577.jpg",
        "https://content.rozetka.com.ua/goods/images/big/148931583.jpg"
      ],
      "reviews": []
    },
    {
      "id": 41,
      "name": "Spin Master Paw Patrol Rescue Vehicle",
      "title": "Rescue Vehicle Spin Master Paw Patrol Paw Patrol Basic Car with Driver Tracker",
      "category": "Kids toys",
      "slug": {
        "slug": "spin-master-paw-patrol-rescue-vehicle",
        "category": "kids-toys"
      },
      "description": "If your child dreams of becoming a hero and simply loves the Paw Patrol animated series, then the Tracker Rescue Vehicle with Driver will be to his liking! Tracker is a funny and cheerful puppy of the Basenji breed. He has an excellent sense of smell and hearing. Tracker joined the friendly team “Paw Patrol” in season 3 and immediately won the hearts of young fans. With his rescue vehicle, Tracker will overcome any difficulties.",
      "price": 21,
      "images": [
        "https://content1.rozetka.com.ua/goods/images/big/178242956.jpg",
        "https://content.rozetka.com.ua/goods/images/big/178242959.jpg",
        "https://content2.rozetka.com.ua/goods/images/big/178242961.jpg",
        "https://content2.rozetka.com.ua/goods/images/big/178242962.jpg",
        "https://content2.rozetka.com.ua/goods/images/big/178242965.jpg"
      ],
      "reviews": []
    },
    {
      "id": 42,
      "name": "Cafe at the edge of the world",
      "title": "Cafe at the edge of the world - Streleki J.P.",
      "category": "Books",
      "slug": {
        "slug": "cafe-at-the-edge-of-the-world",
        "category": "books"
      },
      "description": "Stop. Pause the daily hustle and bustle, escape from its networks and look into the cafe at the end of the world. Expand the menu and take a closer look at the last page - there you will read three questions that you have been running from all your life. Why are you here? Are you afraid of death? Are you satisfied?",
      "price": 4,
      "images": [
        "https://content2.rozetka.com.ua/goods/images/big/129306820.png"
      ],
      "reviews": []
    },
    {
      "id": 43,
      "name": "Colony. New dark ages",
      "title": "Colony. New dark ages. Book 1 - Max Kidruk",
      "category": "Books",
      "slug": {
        "slug": "colony-new-dark-ages",
        "category": "books"
      },
      "description": "Humanity on Earth has not yet recovered from Clodis disease, which led to the largest pandemic in half a century, when a new pathogen appears that infects exclusively pregnant women. A group of immunologists is trying to find out what it is and whether its appearance is related to the neutrino bursts recorded around the planet.",
      "price": 13,
      "images": [
        "https://content.rozetka.com.ua/goods/images/big/322158349.jpg"
      ],
      "reviews": []
    },
    {
      "id": 44,
      "name": "Atlantean straightened his shoulders",
      "title": "Atlantean straightened his shoulders. Part 1. Noncontradiction - Rand A.",
      "category": "Books",
      "slug": {
        "slug": "atlantean-straightened-his-shoulders",
        "category": "books"
      },
      "description": "\"Atlas Shrugged\" Ayn Rand's magnus opus, which the author wrote for 12 years, became her loudest bestseller, one of the most influential works of fiction in world literature. According to a poll by the Library of Congress, this is the second book after the Bible that has changed the lives of American readers. The three parts of the trilogy are named in accordance with the basic laws of logic: \"Indisputable\", \"Either-or\", \"A is A\".",
      "price": 8,
      "images": [
        "https://content.rozetka.com.ua/goods/images/big/13778713.jpg"
      ],
      "reviews": []
    }
  ],
  "users": [
    {
      "accessToket": "FwZc0niFKg2MW69aALoyrvEwA9TGY1Dr2F6eiq3TGUPEVPz6xXiP",
      "orders": [
        {
          "orderPrice": 1907,
          "date": "28.07.2023",
          "products": [
            {
              "id": 2,
              "images": [
                "https://www.istore.ua/upload/iblock/829/tmnfw1wgamc0aoik9auyn1higp6syno3/MNY03_7_is.png",
                "https://www.istore.ua/upload/iblock/715/qn20at4242cf3divw62hlf09z98u9jgz/MNY03_6_is.png",
                "https://www.istore.ua/upload/iblock/43f/kq3m3ooe84x9r5wdfmnow398qs1kq5or/MNY03_5_is.png",
                "https://www.istore.ua/upload/iblock/f37/6ehktfkdouwudcg3zcompq17euzk6pfo/MNY03_4_is.png",
                "https://www.istore.ua/upload/iblock/3a6/l4gmwtplf61ogul0thf3u1uj1tfwzge4/MNY03_2_is.png"
              ],
              "name": "Apple iPad Pro",
              "price": 1907,
              "stars": 3.8,
              "category": "Electronics"
            }
          ]
        }
      ],
      "basket": [],
      "favorits": [],
      "name": "sasha",
      "email": "kononucenkosasa4004@gmail.com",
      "password": "asd123!@#asd",
      "id": 1
    }
  ],
  "banner-slides": [
    {
      "id": 1,
      "image": "/slide-1.jpg",
      "imageMobile": "/slide-mobile-1.jpg",
      "link": "cooking-utensils"
    },
    {
      "id": 2,
      "image": "/slide-2.jpg",
      "imageMobile": "/slide-mobile-2.jpg",
      "link": "perfumery"
    },
    {
      "id": 3,
      "image": "/slide-3.jpg",
      "imageMobile": "/slide-mobile-3.jpg",
      "link": "kids-toys"
    },
    {
      "id": 4,
      "image": "/slide-4.jpg",
      "imageMobile": "/slide-mobile-4.jpg",
      "link": "goods-for-gamers"
    },
    {
      "id": 5,
      "image": "/slide-5.jpg",
      "imageMobile": "/slide-mobile-5.jpg",
      "link": "books"
    }
  ]
}